Metadata-Version: 2.4
Name: sparv-sbx-sentiment-kb-sent
Version: 0.4.1
Summary: A sparv plugin for computing sentiment for sentences.
License-Expression: MIT
Classifier: Development Status :: 4 - Beta
Classifier: Intended Audience :: Developers
Classifier: License :: OSI Approved :: MIT License
Classifier: Operating System :: Unix
Classifier: Operating System :: POSIX
Classifier: Programming Language :: Python :: 3.11
Classifier: Programming Language :: Python :: 3.12
Classifier: Programming Language :: Python :: 3.13
Classifier: Programming Language :: Python :: Implementation :: CPython
Classifier: Topic :: Utilities
Requires-Dist: sparv>=5.3.1
Requires-Dist: transformers>=4.56.1
Requires-Python: >=3.11
Project-URL: Bug Tracker, https://github.com/spraakbanken/sparv-sbx-sentiment-kb-sent/issues
Project-URL: Homepage, https://spraakbanken.gu.se
Project-URL: Repository, https://github.com/spraakbanken/sparv-sbx-sentiment-kb-sent
